ec2_instance_tools/__init__.py
ec2_instance_tools/metadata.py
ec2_instance_tools/namer.py
ec2_instance_tools/sshec2.py
ec2_instance_tools/whoami.py
ec2_instance_tools-0.4.0.dist-info/AUTHORS.txt
ec2_instance_tools-0.4.0.dist-info/LICENSE.txt
ec2_instance_tools-0.4.0.dist-info/METADATA
ec2_instance_tools-0.4.0.dist-info/WHEEL
ec2_instance_tools-0.4.0.dist-info/entry_points.txt
ec2_instance_tools-0.4.0.dist-info/top_level.txt
ec2_instance_tools-0.4.0.dist-info/RECORD
