Metadata-Version: 2.1
Name: ec2-instance-tools
Version: 0.4.0
Summary: Useful instrumentation for EC2 instances
Home-page: https://github.com/caltechads/ec2-instance-tools
Author: Caltech IMSS ADS
Author-email: imss-ads-staff@caltech.edu
Keywords: aws,devops
Classifier: Programming Language :: Python :: 3
Classifier: Programming Language :: Python :: 3.7
Classifier: Programming Language :: Python :: 3.8
Classifier: Programming Language :: Python :: 3.9
Classifier: Programming Language :: Python :: 3.10
Classifier: Programming Language :: Python :: 3.11
License-File: LICENSE.txt
License-File: AUTHORS.txt
Requires-Dist: boto3 >=1.10
Requires-Dist: requests >=2.20
Requires-Dist: urllib3 <2
